federations/__init__.py
federations-0.0.1.dist-info/METADATA
federations-0.0.1.dist-info/WHEEL
federations-0.0.1.dist-info/top_level.txt
federations-0.0.1.dist-info/RECORD
